{
    "fecha_guardado": "2026-06-03 05:21:20",
    "vehiculos": [
        {
            "id_unico": "4a2b3ac6-043834082",
            "placa": "123214",
            "hora_ingreso": "2026-06-03 04:38:34",
            "hora_salida": null,
            "total_pagado": null
        },
        {
            "id_unico": "df75d23c-050636851",
            "placa": "123141",
            "hora_ingreso": "2026-06-03 05:06:36",
            "hora_salida": null,
            "total_pagado": null
        },
        {
            "id_unico": "0ac98ceb-051411121",
            "placa": "123412",
            "hora_ingreso": "2026-06-03 05:14:11",
            "hora_salida": null,
            "total_pagado": null
        },
        {
            "id_unico": "a21b7a41-052038476",
            "placa": "OLA1234",
            "hora_ingreso": "2026-06-03 05:20:38",
            "hora_salida": null,
            "total_pagado": null
        }
    ]
}